azure/multiapi/__init__.py
azure/multiapi/cosmosdb/__init__.py
azure/multiapi/cosmosdb/v2017_04_17/__init__.py
azure/multiapi/cosmosdb/v2017_04_17/common/__init__.py
azure/multiapi/cosmosdb/v2017_04_17/common/_auth.py
azure/multiapi/cosmosdb/v2017_04_17/common/_common_conversion.py
azure/multiapi/cosmosdb/v2017_04_17/common/_connection.py
azure/multiapi/cosmosdb/v2017_04_17/common/_constants.py
azure/multiapi/cosmosdb/v2017_04_17/common/_deserialization.py
azure/multiapi/cosmosdb/v2017_04_17/common/_encryption.py
azure/multiapi/cosmosdb/v2017_04_17/common/_error.py
azure/multiapi/cosmosdb/v2017_04_17/common/_serialization.py
azure/multiapi/cosmosdb/v2017_04_17/common/cloudstorageaccount.py
azure/multiapi/cosmosdb/v2017_04_17/common/models.py
azure/multiapi/cosmosdb/v2017_04_17/common/retry.py
azure/multiapi/cosmosdb/v2017_04_17/common/sharedaccesssignature.py
azure/multiapi/cosmosdb/v2017_04_17/common/storageclient.py
azure/multiapi/cosmosdb/v2017_04_17/common/_http/__init__.py
azure/multiapi/cosmosdb/v2017_04_17/common/_http/httpclient.py
azure/multiapi/cosmosdb/v2017_04_17/table/__init__.py
azure/multiapi/cosmosdb/v2017_04_17/table/_deserialization.py
azure/multiapi/cosmosdb/v2017_04_17/table/_encryption.py
azure/multiapi/cosmosdb/v2017_04_17/table/_error.py
azure/multiapi/cosmosdb/v2017_04_17/table/_request.py
azure/multiapi/cosmosdb/v2017_04_17/table/_serialization.py
azure/multiapi/cosmosdb/v2017_04_17/table/models.py
azure/multiapi/cosmosdb/v2017_04_17/table/tablebatch.py
azure/multiapi/cosmosdb/v2017_04_17/table/tableservice.py
azure/multiapi/storage/__init__.py
azure/multiapi/storage/v2015_04_05/__init__.py
azure/multiapi/storage/v2015_04_05/_auth.py
azure/multiapi/storage/v2015_04_05/_common_conversion.py
azure/multiapi/storage/v2015_04_05/_connection.py
azure/multiapi/storage/v2015_04_05/_constants.py
azure/multiapi/storage/v2015_04_05/_deserialization.py
azure/multiapi/storage/v2015_04_05/_error.py
azure/multiapi/storage/v2015_04_05/_serialization.py
azure_multiapi_storage-1.4.1.dist-info/licenses/LICENSE
azure_multiapi_storage-1.4.1.dist-info/METADATA
azure_multiapi_storage-1.4.1.dist-info/WHEEL
azure_multiapi_storage-1.4.1.dist-info/top_level.txt
azure_multiapi_storage-1.4.1.dist-info/RECORD
