Metadata-Version: 2.4
Name: azure-multiapi-storage
Version: 1.4.1
Summary: Microsoft Azure Storage Client Library for Python with multi API version support.
Home-page: https://github.com/Azure/azure-multiapi-storage-python
Author: Microsoft Corporation
Author-email: azpycli@microsoft.com
License: MIT
Classifier: Development Status :: 5 - Production/Stable
Classifier: Intended Audience :: Developers
Classifier: Programming Language :: Python
Classifier: Programming Language :: Python :: 3
Classifier: Programming Language :: Python :: 3.9
Classifier: Programming Language :: Python :: 3.10
Classifier: Programming Language :: Python :: 3.11
Classifier: Programming Language :: Python :: 3.12
Classifier: License :: OSI Approved :: MIT License
Requires-Python: >=3.9.0
License-File: LICENSE
Requires-Dist: azure-common
Requires-Dist: python-dateutil
Requires-Dist: requests
Requires-Dist: azure-core<2.0.0,>=1.10.0
Requires-Dist: msrest>=0.6.18
Requires-Dist: cryptography>=2.1.4
Dynamic: author
Dynamic: author-email
Dynamic: classifier
Dynamic: description
Dynamic: home-page
Dynamic: license
Dynamic: license-file
Dynamic: requires-dist
Dynamic: requires-python
Dynamic: summary
